setup.py
src/pyjld/__init__.py
src/pyjld.os.egg-info/PKG-INFO
src/pyjld.os.egg-info/SOURCES.txt
src/pyjld.os.egg-info/dependency_links.txt
src/pyjld.os.egg-info/namespace_packages.txt
src/pyjld.os.egg-info/top_level.txt
src/pyjld.os.egg-info/zip-safe
src/pyjld/os/__init__.py
src/pyjld/os/tools.py