Metadata-Version: 1.0
Name: pyjld.os
Version: 0.8
Summary: pyjld.os package
Home-page: http://pyjld.googlecode.com/svn/trunk/pyjld.os/tags/0.8/docs/index.html
Author: Jean-Lou Dupont
Author-email: python (at) jldupont.com
License: UNKNOWN
Platform: UNKNOWN
Classifier: Development Status :: 4 - Beta
Classifier: Intended Audience :: Developers
Classifier: License :: Public Domain
Classifier: Programming Language :: Python
Classifier: Topic :: Software Development :: Libraries :: Python Modules
Classifier: Operating System :: Microsoft :: Windows
Classifier: Operating System :: POSIX
